busca_municipio/__init__.py
busca_municipio/buscador.py
busca_municipio/municipios.txt
busca_municipio-1.0.1.dist-info/licenses/LICENSE
busca_municipio-1.0.1.dist-info/METADATA
busca_municipio-1.0.1.dist-info/WHEEL
busca_municipio-1.0.1.dist-info/top_level.txt
busca_municipio-1.0.1.dist-info/RECORD
