Metadata-Version: 2.4
Name: busca-municipio
Version: 1.0.1
Summary: Búsqueda de municipios españoles mediante similitud de texto
Author-email: Tu Nombre <tu@email.com>
License: MIT
Requires-Python: >=3.9
License-File: LICENSE
Dynamic: license-file
